eccodes/__init__.py
eccodes/__main__.py
eccodes/eccodes.py
eccodes/messages.py
eccodes/high_level/__init__.py
eccodes/high_level/bufr.py
eccodes/high_level/codesfile.py
eccodes/high_level/codesmessage.py
eccodes/high_level/gribfile.py
eccodes/high_level/gribindex.py
eccodes/high_level/gribmessage.py
gribapi/__init__.py
gribapi/bindings.py
gribapi/eccodes.h
gribapi/errors.py
gribapi/grib_api.h
gribapi/gribapi.py
eccodes_python-0.9.9.dist-info/LICENSE
eccodes_python-0.9.9.dist-info/METADATA
eccodes_python-0.9.9.dist-info/WHEEL
eccodes_python-0.9.9.dist-info/top_level.txt
eccodes_python-0.9.9.dist-info/zip-safe
eccodes_python-0.9.9.dist-info/RECORD
